[
  {
    "line": 2,
    "elements": [
      {
        "start_timestamp": "2021-11-09T15:58:22.912Z",
        "before": [
          {
            "result": {
              "duration": 1994700,
              "status": "passed"
            },
            "match": {
              "location": "stepdefinitions.Hooks.setUp()"
            }
          }
        ],
        "line": 5,
        "name": "TC07 istenen kelimenin oldugunu test etme",
        "description": "",
        "id": "us1003-kullanici-istedigi-kelime-icin-arama-yapip--sonucu-test-eder;tc07-istenen-kelimenin-oldugunu-test-etme",
        "after": [
          {
            "result": {
              "duration": 2442394000,
              "status": "passed"
            },
            "match": {
              "location": "stepdefinitions.Hooks.tearDown(io.cucumber.java.Scenario)"
            }
          }
        ],
        "type": "scenario",
        "keyword": "Scenario",
        "steps": [
          {
            "result": {
              "duration": 6459169900,
              "status": "passed"
            },
            "line": 6,
            "name": "kullanici \"amazonUrl\" sayfasina gider",
            "match": {
              "arguments": [
                {
                  "val": "\"amazonUrl\"",
                  "offset": 10
                }
              ],
              "location": "stepdefinitions.amazonStepDefinitions.kullaniciSayfasinaGider(java.lang.String)"
            },
            "keyword": "Given "
          },
          {
            "result": {
              "duration": 1908411100,
              "status": "passed"
            },
            "line": 7,
            "name": "\"armut\" icin arama yapar",
            "match": {
              "arguments": [
                {
                  "val": "\"armut\"",
                  "offset": 0
                }
              ],
              "location": "stepdefinitions.amazonStepDefinitions.icinAramaYapar(java.lang.String)"
            },
            "keyword": "And "
          },
          {
            "result": {
              "duration": 72805600,
              "status": "passed"
            },
            "line": 8,
            "name": "sonucun \"armut\" icerdigini test eder",
            "match": {
              "arguments": [
                {
                  "val": "\"armut\"",
                  "offset": 8
                }
              ],
              "location": "stepdefinitions.amazonStepDefinitions.sonucunIcerdiginiTestEder(java.lang.String)"
            },
            "keyword": "Then "
          },
          {
            "result": {
              "duration": 754455600,
              "status": "passed"
            },
            "line": 9,
            "name": "sayfayi kapatir",
            "match": {
              "location": "stepdefinitions.amazonStepDefinitions.sayfayi_kapatir()"
            },
            "keyword": "And "
          }
        ],
        "tags": [
          {
            "name": "@Paralel2"
          },
          {
            "name": "@rapor2"
          }
        ]
      }
    ],
    "name": "US1003 kullanici istedigi kelime icin arama yapip, sonucu test eder",
    "description": "",
    "id": "us1003-kullanici-istedigi-kelime-icin-arama-yapip--sonucu-test-eder",
    "keyword": "Feature",
    "uri": "file:src/test/resources/features/US1003_amazonParametreliArama.feature",
    "tags": [
      {
        "name": "@Paralel2",
        "type": "Tag",
        "location": {
          "line": 1,
          "column": 1
        }
      }
    ]
  },
  {
    "line": 2,
    "elements": [
      {
        "start_timestamp": "2021-11-09T15:58:34.595Z",
        "before": [
          {
            "result": {
              "duration": 997900,
              "status": "passed"
            },
            "match": {
              "location": "stepdefinitions.Hooks.setUp()"
            }
          }
        ],
        "line": 15,
        "name": "TC09 amazonda verilen bir listeyi aratip, var olduklarini test ediniz",
        "description": "",
        "id": "us1005-amazonda-liste-ile-arama;tc09-amazonda-verilen-bir-listeyi-aratip--var-olduklarini-test-ediniz;;2",
        "after": [
          {
            "result": {
              "duration": 2347933000,
              "status": "passed"
            },
            "match": {
              "location": "stepdefinitions.Hooks.tearDown(io.cucumber.java.Scenario)"
            }
          }
        ],
        "type": "scenario",
        "keyword": "Scenario Outline",
        "steps": [
          {
            "result": {
              "duration": 4469758500,
              "status": "passed"
            },
            "line": 6,
            "name": "kullanici \"amazonUrl\" sayfasina gider",
            "match": {
              "arguments": [
                {
                  "val": "\"amazonUrl\"",
                  "offset": 10
                }
              ],
              "location": "stepdefinitions.amazonStepDefinitions.kullaniciSayfasinaGider(java.lang.String)"
            },
            "keyword": "Given "
          },
          {
            "result": {
              "duration": 2605077700,
              "status": "passed"
            },
            "line": 7,
            "name": "\"nutella\" icin arama yapar",
            "match": {
              "arguments": [
                {
                  "val": "\"nutella\"",
                  "offset": 0
                }
              ],
              "location": "stepdefinitions.amazonStepDefinitions.icinAramaYapar(java.lang.String)"
            },
            "keyword": "Then "
          },
          {
            "result": {
              "duration": 24948900,
              "status": "passed"
            },
            "line": 8,
            "name": "sonuc sayisini yazdirir",
            "match": {
              "location": "stepdefinitions.amazonStepDefinitions.sonucSayisiniYazdirir()"
            },
            "keyword": "And "
          },
          {
            "result": {
              "duration": 19899600,
              "status": "passed"
            },
            "line": 9,
            "name": "sonucun \"nutella\" icerdigini test eder",
            "match": {
              "arguments": [
                {
                  "val": "\"nutella\"",
                  "offset": 8
                }
              ],
              "location": "stepdefinitions.amazonStepDefinitions.sonucunIcerdiginiTestEder(java.lang.String)"
            },
            "keyword": "And "
          },
          {
            "result": {
              "duration": 681592400,
              "status": "passed"
            },
            "line": 10,
            "name": "sayfayi kapatir",
            "match": {
              "location": "stepdefinitions.amazonStepDefinitions.sayfayi_kapatir()"
            },
            "keyword": "Then "
          }
        ],
        "tags": [
          {
            "name": "@Paralel2"
          }
        ]
      },
      {
        "start_timestamp": "2021-11-09T15:58:44.753Z",
        "before": [
          {
            "result": {
              "status": "passed"
            },
            "match": {
              "location": "stepdefinitions.Hooks.setUp()"
            }
          }
        ],
        "line": 16,
        "name": "TC09 amazonda verilen bir listeyi aratip, var olduklarini test ediniz",
        "description": "",
        "id": "us1005-amazonda-liste-ile-arama;tc09-amazonda-verilen-bir-listeyi-aratip--var-olduklarini-test-ediniz;;3",
        "after": [
          {
            "result": {
              "duration": 2366076600,
              "status": "passed"
            },
            "match": {
              "location": "stepdefinitions.Hooks.tearDown(io.cucumber.java.Scenario)"
            }
          }
        ],
        "type": "scenario",
        "keyword": "Scenario Outline",
        "steps": [
          {
            "result": {
              "duration": 4251488900,
              "status": "passed"
            },
            "line": 6,
            "name": "kullanici \"amazonUrl\" sayfasina gider",
            "match": {
              "arguments": [
                {
                  "val": "\"amazonUrl\"",
                  "offset": 10
                }
              ],
              "location": "stepdefinitions.amazonStepDefinitions.kullaniciSayfasinaGider(java.lang.String)"
            },
            "keyword": "Given "
          },
          {
            "result": {
              "duration": 3674431300,
              "status": "passed"
            },
            "line": 7,
            "name": "\"java\" icin arama yapar",
            "match": {
              "arguments": [
                {
                  "val": "\"java\"",
                  "offset": 0
                }
              ],
              "location": "stepdefinitions.amazonStepDefinitions.icinAramaYapar(java.lang.String)"
            },
            "keyword": "Then "
          },
          {
            "result": {
              "duration": 62832100,
              "status": "passed"
            },
            "line": 8,
            "name": "sonuc sayisini yazdirir",
            "match": {
              "location": "stepdefinitions.amazonStepDefinitions.sonucSayisiniYazdirir()"
            },
            "keyword": "And "
          },
          {
            "result": {
              "duration": 36633900,
              "status": "passed"
            },
            "line": 9,
            "name": "sonucun \"java\" icerdigini test eder",
            "match": {
              "arguments": [
                {
                  "val": "\"java\"",
                  "offset": 8
                }
              ],
              "location": "stepdefinitions.amazonStepDefinitions.sonucunIcerdiginiTestEder(java.lang.String)"
            },
            "keyword": "And "
          },
          {
            "result": {
              "duration": 793302600,
              "status": "passed"
            },
            "line": 10,
            "name": "sayfayi kapatir",
            "match": {
              "location": "stepdefinitions.amazonStepDefinitions.sayfayi_kapatir()"
            },
            "keyword": "Then "
          }
        ],
        "tags": [
          {
            "name": "@Paralel2"
          }
        ]
      },
      {
        "start_timestamp": "2021-11-09T15:58:55.947Z",
        "before": [
          {
            "result": {
              "status": "passed"
            },
            "match": {
              "location": "stepdefinitions.Hooks.setUp()"
            }
          }
        ],
        "line": 17,
        "name": "TC09 amazonda verilen bir listeyi aratip, var olduklarini test ediniz",
        "description": "",
        "id": "us1005-amazonda-liste-ile-arama;tc09-amazonda-verilen-bir-listeyi-aratip--var-olduklarini-test-ediniz;;4",
        "after": [
          {
            "result": {
              "duration": 2500622800,
              "status": "passed"
            },
            "match": {
              "location": "stepdefinitions.Hooks.tearDown(io.cucumber.java.Scenario)"
            }
          }
        ],
        "type": "scenario",
        "keyword": "Scenario Outline",
        "steps": [
          {
            "result": {
              "duration": 3290894500,
              "status": "passed"
            },
            "line": 6,
            "name": "kullanici \"amazonUrl\" sayfasina gider",
            "match": {
              "arguments": [
                {
                  "val": "\"amazonUrl\"",
                  "offset": 10
                }
              ],
              "location": "stepdefinitions.amazonStepDefinitions.kullaniciSayfasinaGider(java.lang.String)"
            },
            "keyword": "Given "
          },
          {
            "result": {
              "duration": 3990617300,
              "status": "passed"
            },
            "line": 7,
            "name": "\"ipod\" icin arama yapar",
            "match": {
              "arguments": [
                {
                  "val": "\"ipod\"",
                  "offset": 0
                }
              ],
              "location": "stepdefinitions.amazonStepDefinitions.icinAramaYapar(java.lang.String)"
            },
            "keyword": "Then "
          },
          {
            "result": {
              "duration": 81779800,
              "status": "passed"
            },
            "line": 8,
            "name": "sonuc sayisini yazdirir",
            "match": {
              "location": "stepdefinitions.amazonStepDefinitions.sonucSayisiniYazdirir()"
            },
            "keyword": "And "
          },
          {
            "result": {
              "duration": 29920300,
              "status": "passed"
            },
            "line": 9,
            "name": "sonucun \"ipod\" icerdigini test eder",
            "match": {
              "arguments": [
                {
                  "val": "\"ipod\"",
                  "offset": 8
                }
              ],
              "location": "stepdefinitions.amazonStepDefinitions.sonucunIcerdiginiTestEder(java.lang.String)"
            },
            "keyword": "And "
          },
          {
            "result": {
              "duration": 733063700,
              "status": "passed"
            },
            "line": 10,
            "name": "sayfayi kapatir",
            "match": {
              "location": "stepdefinitions.amazonStepDefinitions.sayfayi_kapatir()"
            },
            "keyword": "Then "
          }
        ],
        "tags": [
          {
            "name": "@Paralel2"
          }
        ]
      },
      {
        "start_timestamp": "2021-11-09T15:59:06.585Z",
        "before": [
          {
            "result": {
              "status": "passed"
            },
            "match": {
              "location": "stepdefinitions.Hooks.setUp()"
            }
          }
        ],
        "line": 18,
        "name": "TC09 amazonda verilen bir listeyi aratip, var olduklarini test ediniz",
        "description": "",
        "id": "us1005-amazonda-liste-ile-arama;tc09-amazonda-verilen-bir-listeyi-aratip--var-olduklarini-test-ediniz;;5",
        "after": [
          {
            "result": {
              "duration": 2176735600,
              "status": "passed"
            },
            "match": {
              "location": "stepdefinitions.Hooks.tearDown(io.cucumber.java.Scenario)"
            }
          }
        ],
        "type": "scenario",
        "keyword": "Scenario Outline",
        "steps": [
          {
            "result": {
              "duration": 4103833200,
              "status": "passed"
            },
            "line": 6,
            "name": "kullanici \"amazonUrl\" sayfasina gider",
            "match": {
              "arguments": [
                {
                  "val": "\"amazonUrl\"",
                  "offset": 10
                }
              ],
              "location": "stepdefinitions.amazonStepDefinitions.kullaniciSayfasinaGider(java.lang.String)"
            },
            "keyword": "Given "
          },
          {
            "result": {
              "duration": 1702650500,
              "status": "passed"
            },
            "line": 7,
            "name": "\"armut\" icin arama yapar",
            "match": {
              "arguments": [
                {
                  "val": "\"armut\"",
                  "offset": 0
                }
              ],
              "location": "stepdefinitions.amazonStepDefinitions.icinAramaYapar(java.lang.String)"
            },
            "keyword": "Then "
          },
          {
            "result": {
              "duration": 89277900,
              "status": "passed"
            },
            "line": 8,
            "name": "sonuc sayisini yazdirir",
            "match": {
              "location": "stepdefinitions.amazonStepDefinitions.sonucSayisiniYazdirir()"
            },
            "keyword": "And "
          },
          {
            "result": {
              "duration": 99244200,
              "status": "passed"
            },
            "line": 9,
            "name": "sonucun \"armut\" icerdigini test eder",
            "match": {
              "arguments": [
                {
                  "val": "\"armut\"",
                  "offset": 8
                }
              ],
              "location": "stepdefinitions.amazonStepDefinitions.sonucunIcerdiginiTestEder(java.lang.String)"
            },
            "keyword": "And "
          },
          {
            "result": {
              "duration": 884027300,
              "status": "passed"
            },
            "line": 10,
            "name": "sayfayi kapatir",
            "match": {
              "location": "stepdefinitions.amazonStepDefinitions.sayfayi_kapatir()"
            },
            "keyword": "Then "
          }
        ],
        "tags": [
          {
            "name": "@Paralel2"
          }
        ]
      },
      {
        "start_timestamp": "2021-11-09T15:59:15.647Z",
        "before": [
          {
            "result": {
              "duration": 995300,
              "status": "passed"
            },
            "match": {
              "location": "stepdefinitions.Hooks.setUp()"
            }
          }
        ],
        "line": 19,
        "name": "TC09 amazonda verilen bir listeyi aratip, var olduklarini test ediniz",
        "description": "",
        "id": "us1005-amazonda-liste-ile-arama;tc09-amazonda-verilen-bir-listeyi-aratip--var-olduklarini-test-ediniz;;6",
        "after": [
          {
            "result": {
              "duration": 2300954000,
              "status": "passed"
            },
            "match": {
              "location": "stepdefinitions.Hooks.tearDown(io.cucumber.java.Scenario)"
            }
          }
        ],
        "type": "scenario",
        "keyword": "Scenario Outline",
        "steps": [
          {
            "result": {
              "duration": 9486962700,
              "status": "passed"
            },
            "line": 6,
            "name": "kullanici \"amazonUrl\" sayfasina gider",
            "match": {
              "arguments": [
                {
                  "val": "\"amazonUrl\"",
                  "offset": 10
                }
              ],
              "location": "stepdefinitions.amazonStepDefinitions.kullaniciSayfasinaGider(java.lang.String)"
            },
            "keyword": "Given "
          },
          {
            "result": {
              "duration": 2854958000,
              "status": "passed"
            },
            "line": 7,
            "name": "\"Apple\" icin arama yapar",
            "match": {
              "arguments": [
                {
                  "val": "\"Apple\"",
                  "offset": 0
                }
              ],
              "location": "stepdefinitions.amazonStepDefinitions.icinAramaYapar(java.lang.String)"
            },
            "keyword": "Then "
          },
          {
            "result": {
              "duration": 98128800,
              "status": "passed"
            },
            "line": 8,
            "name": "sonuc sayisini yazdirir",
            "match": {
              "location": "stepdefinitions.amazonStepDefinitions.sonucSayisiniYazdirir()"
            },
            "keyword": "And "
          },
          {
            "result": {
              "duration": 23064500,
              "status": "passed"
            },
            "line": 9,
            "name": "sonucun \"Apple\" icerdigini test eder",
            "match": {
              "arguments": [
                {
                  "val": "\"Apple\"",
                  "offset": 8
                }
              ],
              "location": "stepdefinitions.amazonStepDefinitions.sonucunIcerdiginiTestEder(java.lang.String)"
            },
            "keyword": "And "
          },
          {
            "result": {
              "duration": 755432600,
              "status": "passed"
            },
            "line": 10,
            "name": "sayfayi kapatir",
            "match": {
              "location": "stepdefinitions.amazonStepDefinitions.sayfayi_kapatir()"
            },
            "keyword": "Then "
          }
        ],
        "tags": [
          {
            "name": "@Paralel2"
          }
        ]
      }
    ],
    "name": "US1005 amazonda liste ile arama",
    "description": "",
    "id": "us1005-amazonda-liste-ile-arama",
    "keyword": "Feature",
    "uri": "file:src/test/resources/features/US1005_scenarioOutline.feature",
    "tags": [
      {
        "name": "@Paralel2",
        "type": "Tag",
        "location": {
          "line": 1,
          "column": 1
        }
      }
    ]
  },
  {
    "line": 2,
    "elements": [
      {
        "start_timestamp": "2021-11-09T15:59:31.192Z",
        "before": [
          {
            "result": {
              "status": "passed"
            },
            "match": {
              "location": "stepdefinitions.Hooks.setUp()"
            }
          }
        ],
        "line": 19,
        "name": "TC10 Farkli kullanici isimleri ile negative test",
        "description": "",
        "id": "us1006-concort-hotels-sayfasinda-farkli-kullanici-adlari-ile-negative-test;tc10-farkli-kullanici-isimleri-ile-negative-test;;2",
        "after": [
          {
            "result": {
              "duration": 2152891600,
              "status": "passed"
            },
            "match": {
              "location": "stepdefinitions.Hooks.tearDown(io.cucumber.java.Scenario)"
            }
          }
        ],
        "type": "scenario",
        "keyword": "Scenario Outline",
        "steps": [
          {
            "result": {
              "duration": 10363702200,
              "status": "passed"
            },
            "line": 7,
            "name": "kullanici \"CHQAUrl\" sayfasina gider",
            "match": {
              "arguments": [
                {
                  "val": "\"CHQAUrl\"",
                  "offset": 10
                }
              ],
              "location": "stepdefinitions.amazonStepDefinitions.kullaniciSayfasinaGider(java.lang.String)"
            },
            "keyword": "Given "
          },
          {
            "result": {
              "duration": 830478200,
              "status": "passed"
            },
            "line": 8,
            "name": "CH login linkine tiklar",
            "match": {
              "location": "stepdefinitions.CHQAStepDefinitions.ch_login_linkine_tiklar()"
            },
            "keyword": "Then "
          },
          {
            "result": {
              "duration": 75265400,
              "status": "passed"
            },
            "line": 9,
            "name": "CH username kutusuna \"Manager5\" yazar",
            "match": {
              "arguments": [
                {
                  "val": "\"Manager5\"",
                  "offset": 21
                }
              ],
              "location": "stepdefinitions.CHQAStepDefinitions.ch_username_kutusuna_yazar(java.lang.String)"
            },
            "keyword": "And "
          },
          {
            "result": {
              "duration": 79527300,
              "status": "passed"
            },
            "line": 10,
            "name": "CH password kutusuna \"anager5!\" yazar",
            "match": {
              "arguments": [
                {
                  "val": "\"anager5!\"",
                  "offset": 21
                }
              ],
              "location": "stepdefinitions.CHQAStepDefinitions.ch_password_kutusuna_yazar(java.lang.String)"
            },
            "keyword": "And "
          },
          {
            "result": {
              "duration": 1211394700,
              "status": "passed"
            },
            "line": 11,
            "name": "CH login butonuna basar",
            "match": {
              "location": "stepdefinitions.CHQAStepDefinitions.ch_login_butonuna_basar()"
            },
            "keyword": "And "
          },
          {
            "result": {
              "duration": 50913800,
              "status": "passed"
            },
            "line": 12,
            "name": "giris yapilamadigini test eder",
            "match": {
              "location": "stepdefinitions.CHQAStepDefinitions.giris_yapilamadigini_test_eder()"
            },
            "keyword": "Then "
          },
          {
            "result": {
              "duration": 637774300,
              "status": "passed"
            },
            "line": 13,
            "name": "sayfayi kapatir",
            "match": {
              "location": "stepdefinitions.amazonStepDefinitions.sayfayi_kapatir()"
            },
            "keyword": "And "
          }
        ],
        "tags": [
          {
            "name": "@Paralel2"
          },
          {
            "name": "@CH"
          }
        ]
      },
      {
        "start_timestamp": "2021-11-09T15:59:46.598Z",
        "before": [
          {
            "result": {
              "status": "passed"
            },
            "match": {
              "location": "stepdefinitions.Hooks.setUp()"
            }
          }
        ],
        "line": 20,
        "name": "TC10 Farkli kullanici isimleri ile negative test",
        "description": "",
        "id": "us1006-concort-hotels-sayfasinda-farkli-kullanici-adlari-ile-negative-test;tc10-farkli-kullanici-isimleri-ile-negative-test;;3",
        "after": [
          {
            "result": {
              "duration": 2181660100,
              "status": "passed"
            },
            "match": {
              "location": "stepdefinitions.Hooks.tearDown(io.cucumber.java.Scenario)"
            }
          }
        ],
        "type": "scenario",
        "keyword": "Scenario Outline",
        "steps": [
          {
            "result": {
              "duration": 11365956600,
              "status": "passed"
            },
            "line": 7,
            "name": "kullanici \"CHQAUrl\" sayfasina gider",
            "match": {
              "arguments": [
                {
                  "val": "\"CHQAUrl\"",
                  "offset": 10
                }
              ],
              "location": "stepdefinitions.amazonStepDefinitions.kullaniciSayfasinaGider(java.lang.String)"
            },
            "keyword": "Given "
          },
          {
            "result": {
              "duration": 869090700,
              "status": "passed"
            },
            "line": 8,
            "name": "CH login linkine tiklar",
            "match": {
              "location": "stepdefinitions.CHQAStepDefinitions.ch_login_linkine_tiklar()"
            },
            "keyword": "Then "
          },
          {
            "result": {
              "duration": 85291500,
              "status": "passed"
            },
            "line": 9,
            "name": "CH username kutusuna \"Manager6\" yazar",
            "match": {
              "arguments": [
                {
                  "val": "\"Manager6\"",
                  "offset": 21
                }
              ],
              "location": "stepdefinitions.CHQAStepDefinitions.ch_username_kutusuna_yazar(java.lang.String)"
            },
            "keyword": "And "
          },
          {
            "result": {
              "duration": 70396000,
              "status": "passed"
            },
            "line": 10,
            "name": "CH password kutusuna \"Manager6!\" yazar",
            "match": {
              "arguments": [
                {
                  "val": "\"Manager6!\"",
                  "offset": 21
                }
              ],
              "location": "stepdefinitions.CHQAStepDefinitions.ch_password_kutusuna_yazar(java.lang.String)"
            },
            "keyword": "And "
          },
          {
            "result": {
              "duration": 724689400,
              "status": "passed"
            },
            "line": 11,
            "name": "CH login butonuna basar",
            "match": {
              "location": "stepdefinitions.CHQAStepDefinitions.ch_login_butonuna_basar()"
            },
            "keyword": "And "
          },
          {
            "result": {
              "duration": 56207200,
              "status": "passed"
            },
            "line": 12,
            "name": "giris yapilamadigini test eder",
            "match": {
              "location": "stepdefinitions.CHQAStepDefinitions.giris_yapilamadigini_test_eder()"
            },
            "keyword": "Then "
          },
          {
            "result": {
              "duration": 643626800,
              "status": "passed"
            },
            "line": 13,
            "name": "sayfayi kapatir",
            "match": {
              "location": "stepdefinitions.amazonStepDefinitions.sayfayi_kapatir()"
            },
            "keyword": "And "
          }
        ],
        "tags": [
          {
            "name": "@Paralel2"
          },
          {
            "name": "@CH"
          }
        ]
      },
      {
        "start_timestamp": "2021-11-09T16:00:02.607Z",
        "before": [
          {
            "result": {
              "status": "passed"
            },
            "match": {
              "location": "stepdefinitions.Hooks.setUp()"
            }
          }
        ],
        "line": 21,
        "name": "TC10 Farkli kullanici isimleri ile negative test",
        "description": "",
        "id": "us1006-concort-hotels-sayfasinda-farkli-kullanici-adlari-ile-negative-test;tc10-farkli-kullanici-isimleri-ile-negative-test;;4",
        "after": [
          {
            "result": {
              "duration": 2171285500,
              "status": "passed"
            },
            "match": {
              "location": "stepdefinitions.Hooks.tearDown(io.cucumber.java.Scenario)"
            }
          }
        ],
        "type": "scenario",
        "keyword": "Scenario Outline",
        "steps": [
          {
            "result": {
              "duration": 11644586500,
              "status": "passed"
            },
            "line": 7,
            "name": "kullanici \"CHQAUrl\" sayfasina gider",
            "match": {
              "arguments": [
                {
                  "val": "\"CHQAUrl\"",
                  "offset": 10
                }
              ],
              "location": "stepdefinitions.amazonStepDefinitions.kullaniciSayfasinaGider(java.lang.String)"
            },
            "keyword": "Given "
          },
          {
            "result": {
              "duration": 740471800,
              "status": "passed"
            },
            "line": 8,
            "name": "CH login linkine tiklar",
            "match": {
              "location": "stepdefinitions.CHQAStepDefinitions.ch_login_linkine_tiklar()"
            },
            "keyword": "Then "
          },
          {
            "result": {
              "duration": 81952100,
              "status": "passed"
            },
            "line": 9,
            "name": "CH username kutusuna \"Manager7\" yazar",
            "match": {
              "arguments": [
                {
                  "val": "\"Manager7\"",
                  "offset": 21
                }
              ],
              "location": "stepdefinitions.CHQAStepDefinitions.ch_username_kutusuna_yazar(java.lang.String)"
            },
            "keyword": "And "
          },
          {
            "result": {
              "duration": 63842900,
              "status": "passed"
            },
            "line": 10,
            "name": "CH password kutusuna \"anager7!\" yazar",
            "match": {
              "arguments": [
                {
                  "val": "\"anager7!\"",
                  "offset": 21
                }
              ],
              "location": "stepdefinitions.CHQAStepDefinitions.ch_password_kutusuna_yazar(java.lang.String)"
            },
            "keyword": "And "
          },
          {
            "result": {
              "duration": 789573700,
              "status": "passed"
            },
            "line": 11,
            "name": "CH login butonuna basar",
            "match": {
              "location": "stepdefinitions.CHQAStepDefinitions.ch_login_butonuna_basar()"
            },
            "keyword": "And "
          },
          {
            "result": {
              "duration": 37697000,
              "status": "passed"
            },
            "line": 12,
            "name": "giris yapilamadigini test eder",
            "match": {
              "location": "stepdefinitions.CHQAStepDefinitions.giris_yapilamadigini_test_eder()"
            },
            "keyword": "Then "
          },
          {
            "result": {
              "duration": 635691800,
              "status": "passed"
            },
            "line": 13,
            "name": "sayfayi kapatir",
            "match": {
              "location": "stepdefinitions.amazonStepDefinitions.sayfayi_kapatir()"
            },
            "keyword": "And "
          }
        ],
        "tags": [
          {
            "name": "@Paralel2"
          },
          {
            "name": "@CH"
          }
        ]
      },
      {
        "start_timestamp": "2021-11-09T16:00:18.777Z",
        "before": [
          {
            "result": {
              "status": "passed"
            },
            "match": {
              "location": "stepdefinitions.Hooks.setUp()"
            }
          }
        ],
        "line": 22,
        "name": "TC10 Farkli kullanici isimleri ile negative test",
        "description": "",
        "id": "us1006-concort-hotels-sayfasinda-farkli-kullanici-adlari-ile-negative-test;tc10-farkli-kullanici-isimleri-ile-negative-test;;5",
        "after": [
          {
            "result": {
              "duration": 2175420300,
              "status": "passed"
            },
            "match": {
              "location": "stepdefinitions.Hooks.tearDown(io.cucumber.java.Scenario)"
            }
          }
        ],
        "type": "scenario",
        "keyword": "Scenario Outline",
        "steps": [
          {
            "result": {
              "duration": 15314019700,
              "status": "passed"
            },
            "line": 7,
            "name": "kullanici \"CHQAUrl\" sayfasina gider",
            "match": {
              "arguments": [
                {
                  "val": "\"CHQAUrl\"",
                  "offset": 10
                }
              ],
              "location": "stepdefinitions.amazonStepDefinitions.kullaniciSayfasinaGider(java.lang.String)"
            },
            "keyword": "Given "
          },
          {
            "result": {
              "duration": 767014600,
              "status": "passed"
            },
            "line": 8,
            "name": "CH login linkine tiklar",
            "match": {
              "location": "stepdefinitions.CHQAStepDefinitions.ch_login_linkine_tiklar()"
            },
            "keyword": "Then "
          },
          {
            "result": {
              "duration": 112155600,
              "status": "passed"
            },
            "line": 9,
            "name": "CH username kutusuna \"Manager8\" yazar",
            "match": {
              "arguments": [
                {
                  "val": "\"Manager8\"",
                  "offset": 21
                }
              ],
              "location": "stepdefinitions.CHQAStepDefinitions.ch_username_kutusuna_yazar(java.lang.String)"
            },
            "keyword": "And "
          },
          {
            "result": {
              "duration": 89769400,
              "status": "passed"
            },
            "line": 10,
            "name": "CH password kutusuna \"anager8!\" yazar",
            "match": {
              "arguments": [
                {
                  "val": "\"anager8!\"",
                  "offset": 21
                }
              ],
              "location": "stepdefinitions.CHQAStepDefinitions.ch_password_kutusuna_yazar(java.lang.String)"
            },
            "keyword": "And "
          },
          {
            "result": {
              "duration": 774349900,
              "status": "passed"
            },
            "line": 11,
            "name": "CH login butonuna basar",
            "match": {
              "location": "stepdefinitions.CHQAStepDefinitions.ch_login_butonuna_basar()"
            },
            "keyword": "And "
          },
          {
            "result": {
              "duration": 43391700,
              "status": "passed"
            },
            "line": 12,
            "name": "giris yapilamadigini test eder",
            "match": {
              "location": "stepdefinitions.CHQAStepDefinitions.giris_yapilamadigini_test_eder()"
            },
            "keyword": "Then "
          },
          {
            "result": {
              "duration": 652398800,
              "status": "passed"
            },
            "line": 13,
            "name": "sayfayi kapatir",
            "match": {
              "location": "stepdefinitions.amazonStepDefinitions.sayfayi_kapatir()"
            },
            "keyword": "And "
          }
        ],
        "tags": [
          {
            "name": "@Paralel2"
          },
          {
            "name": "@CH"
          }
        ]
      },
      {
        "start_timestamp": "2021-11-09T16:00:38.721Z",
        "before": [
          {
            "result": {
              "duration": 996100,
              "status": "passed"
            },
            "match": {
              "location": "stepdefinitions.Hooks.setUp()"
            }
          }
        ],
        "line": 23,
        "name": "TC10 Farkli kullanici isimleri ile negative test",
        "description": "",
        "id": "us1006-concort-hotels-sayfasinda-farkli-kullanici-adlari-ile-negative-test;tc10-farkli-kullanici-isimleri-ile-negative-test;;6",
        "after": [
          {
            "result": {
              "duration": 2150082900,
              "status": "passed"
            },
            "match": {
              "location": "stepdefinitions.Hooks.tearDown(io.cucumber.java.Scenario)"
            }
          }
        ],
        "type": "scenario",
        "keyword": "Scenario Outline",
        "steps": [
          {
            "result": {
              "duration": 12325686500,
              "status": "passed"
            },
            "line": 7,
            "name": "kullanici \"CHQAUrl\" sayfasina gider",
            "match": {
              "arguments": [
                {
                  "val": "\"CHQAUrl\"",
                  "offset": 10
                }
              ],
              "location": "stepdefinitions.amazonStepDefinitions.kullaniciSayfasinaGider(java.lang.String)"
            },
            "keyword": "Given "
          },
          {
            "result": {
              "duration": 1078036000,
              "status": "passed"
            },
            "line": 8,
            "name": "CH login linkine tiklar",
            "match": {
              "location": "stepdefinitions.CHQAStepDefinitions.ch_login_linkine_tiklar()"
            },
            "keyword": "Then "
          },
          {
            "result": {
              "duration": 82524100,
              "status": "passed"
            },
            "line": 9,
            "name": "CH username kutusuna \"Manager9\" yazar",
            "match": {
              "arguments": [
                {
                  "val": "\"Manager9\"",
                  "offset": 21
                }
              ],
              "location": "stepdefinitions.CHQAStepDefinitions.ch_username_kutusuna_yazar(java.lang.String)"
            },
            "keyword": "And "
          },
          {
            "result": {
              "duration": 76326800,
              "status": "passed"
            },
            "line": 10,
            "name": "CH password kutusuna \"anager9!\" yazar",
            "match": {
              "arguments": [
                {
                  "val": "\"anager9!\"",
                  "offset": 21
                }
              ],
              "location": "stepdefinitions.CHQAStepDefinitions.ch_password_kutusuna_yazar(java.lang.String)"
            },
            "keyword": "And "
          },
          {
            "result": {
              "duration": 724956500,
              "status": "passed"
            },
            "line": 11,
            "name": "CH login butonuna basar",
            "match": {
              "location": "stepdefinitions.CHQAStepDefinitions.ch_login_butonuna_basar()"
            },
            "keyword": "And "
          },
          {
            "result": {
              "duration": 52946900,
              "status": "passed"
            },
            "line": 12,
            "name": "giris yapilamadigini test eder",
            "match": {
              "location": "stepdefinitions.CHQAStepDefinitions.giris_yapilamadigini_test_eder()"
            },
            "keyword": "Then "
          },
          {
            "result": {
              "duration": 664516500,
              "status": "passed"
            },
            "line": 13,
            "name": "sayfayi kapatir",
            "match": {
              "location": "stepdefinitions.amazonStepDefinitions.sayfayi_kapatir()"
            },
            "keyword": "And "
          }
        ],
        "tags": [
          {
            "name": "@Paralel2"
          },
          {
            "name": "@CH"
          }
        ]
      }
    ],
    "name": "US1006 concort hotels sayfasinda farkli kullanici adlari ile negative test",
    "description": "",
    "id": "us1006-concort-hotels-sayfasinda-farkli-kullanici-adlari-ile-negative-test",
    "keyword": "Feature",
    "uri": "file:src/test/resources/features/US1006_CooncortHotelsNegativeLoginScenarioOutline.feature",
    "tags": [
      {
        "name": "@Paralel2",
        "type": "Tag",
        "location": {
          "line": 1,
          "column": 1
        }
      }
    ]
  }
]